mscl_rs-0.2.0.dist-info/METADATA
mscl_rs-0.2.0.dist-info/WHEEL
mscl_rs-0.2.0.dist-info/licenses/LICENSE
mscl_rs/__init__.py
mscl_rs/__init__.pyi
mscl_rs/mscl_rs.cpython-314-x86_64-linux-gnu.so
mscl_rs/py.typed
mscl_rs-0.2.0.dist-info/RECORD
