Metadata-Version: 2.4
Name: mscl-rs
Version: 0.2.0
Classifier: Development Status :: 4 - Beta
Classifier: Programming Language :: Python :: 3.10
Classifier: Programming Language :: Python :: 3.11
Classifier: Programming Language :: Python :: 3.12
Classifier: Programming Language :: Python :: 3.13
Classifier: Programming Language :: Python :: 3.14
Classifier: License :: OSI Approved :: MIT License
Classifier: Programming Language :: Rust
Classifier: Operating System :: OS Independent
Classifier: Topic :: Software Development :: Libraries
Classifier: Topic :: Scientific/Engineering :: Physics
License-File: LICENSE
Summary: Parser for MicroStrain Communication Library (MSCL) packets in Rust.
Author-email: Harshil <37377066+harshil21@users.noreply.github.com>
License-Expression: MIT
Requires-Python: >=3.10
Project-URL: Homepage, https://ncsurocketry.org
Project-URL: Source, https://github.com/NCSU-High-Powered-Rocketry-Club/mscl_rs
